bcst/__init__.py
bcst/bcst
bcst/theme.py
bcst/themes/afternoon/index.html
bcst/themes/afternoon/resources.json
bcst/themes/afternoon/css/main.css
bcst/themes/afternoon/js/main.ts
bcst/themes/afternoon/js/dist/main.js
bcst/themes/afternoon/res/favicon.png
bcst/themes/afternoon/res/placeholder.png
bcst/themes/afternoon/res/images/wallpaper.gif
bcst/themes/default/index.html
bcst/themes/default/resources.json
bcst/themes/default/assets/script.js
bcst/themes/default/assets/style.css
bcst/themes/home-term/index.html
bcst/themes/home-term/resources.json
bcst/themes/home-term/css/style.css
bcst/themes/home-term/fonts/roboto-mono-medium.ttf
bcst/themes/home-term/script/script.js
bcst/themes/hrstv/book.png
bcst/themes/hrstv/index.html
bcst/themes/hrstv/resources.json
bcst/themes/hrstv/styles.css
bcst/themes/hrstv/vcrosdmono.ttf
bcst/themes/hungry-hobo/.style.css.swp
bcst/themes/hungry-hobo/index.html
bcst/themes/hungry-hobo/resources.json
bcst/themes/hungry-hobo/style.css
bcst/themes/qhungg/index.html
bcst/themes/qhungg/resources.json
bcst/themes/qhungg/background/background.png
bcst/themes/qhungg/fonts/roboto-mono-medium.ttf
bcst/themes/qhungg/icon/leaf.png
bcst/themes/qhungg/style/style.css
bcst-0.0.9.data/scripts/bcst
libs/__init__.py
libs/args.py
libs/resource.py
libs/theme.py
themes/__init__.py
bcst-0.0.9.dist-info/LICENSE
bcst-0.0.9.dist-info/METADATA
bcst-0.0.9.dist-info/WHEEL
bcst-0.0.9.dist-info/top_level.txt
bcst-0.0.9.dist-info/RECORD
