Metadata-Version: 2.1
Name: bcst
Version: 0.0.9
Summary: A web browser start page generator.
Home-page: https://gitlab.com/manzerbredes/bcst
Author: Loic Guegan
Author-email: manzerbredes@mailbox.org
License: UNKNOWN
Platform: UNKNOWN
Classifier: License :: OSI Approved :: GNU General Public License v3 or later (GPLv3+)
Requires-Dist: jinja2
